[
  {
    "id": 10001,
    "name": "星光套装",
    "type": 1,
    "sub_type": 1,
    "rarity": 4,
    "quality": 4,
    "max_stack": 1,
    "can_trade": false,
    "can_sell": false,
    "can_drop": false,
    "can_destroy": true,
    "bind_type": 1,
    "use_level": 1,
    "use_vocation": 0,
    "expire_type": 0,
    "expire_time": 0,
    "use_skill_ids": [],
    "cooldown": 0,
    "cooldown_group": 0,
    "tags": [
      "costume",
      "suit"
    ]
  },
  {
    "id": 10002,
    "name": "可爱笑脸",
    "type": 1,
    "sub_type": 2,
    "rarity": 3,
    "quality": 3,
    "max_stack": 1,
    "can_trade": true,
    "can_sell": true,
    "can_drop": false,
    "can_destroy": true,
    "bind_type": 0,
    "use_level": 1,
    "use_vocation": 0,
    "expire_type": 0,
    "expire_time": 0,
    "use_skill_ids": [],
    "cooldown": 0,
    "cooldown_group": 0,
    "tags": [
      "costume",
      "face"
    ]
  },
  {
    "id": 20001,
    "name": "生命药水(小)",
    "type": 2,
    "sub_type": 9,
    "rarity": 1,
    "quality": 1,
    "max_stack": 99,
    "can_trade": true,
    "can_sell": true,
    "can_drop": true,
    "can_destroy": true,
    "bind_type": 0,
    "use_level": 1,
    "use_vocation": 0,
    "expire_type": 0,
    "expire_time": 0,
    "use_skill_ids": [],
    "cooldown": 1000,
    "cooldown_group": 1,
    "tags": [
      "consumable",
      "potion",
      "hp"
    ]
  },
  {
    "id": 20002,
    "name": "铁矿石",
    "type": 2,
    "sub_type": 10,
    "rarity": 1,
    "quality": 1,
    "max_stack": 999,
    "can_trade": true,
    "can_sell": true,
    "can_drop": false,
    "can_destroy": true,
    "bind_type": 0,
    "use_level": 1,
    "use_vocation": 0,
    "expire_type": 0,
    "expire_time": 0,
    "use_skill_ids": [],
    "cooldown": 0,
    "cooldown_group": 0,
    "tags": [
      "material",
      "ore"
    ]
  },
  {
    "id": 30001,
    "name": "新手剑",
    "type": 3,
    "sub_type": 12,
    "rarity": 1,
    "quality": 1,
    "max_stack": 1,
    "can_trade": true,
    "can_sell": true,
    "can_drop": true,
    "can_destroy": true,
    "bind_type": 0,
    "use_level": 1,
    "use_vocation": 0,
    "expire_type": 0,
    "expire_time": 0,
    "use_skill_ids": [],
    "cooldown": 0,
    "cooldown_group": 0,
    "tags": [
      "equipment",
      "weapon",
      "sword"
    ]
  },
  {
    "id": 30002,
    "name": "铁制头盔",
    "type": 3,
    "sub_type": 13,
    "rarity": 2,
    "quality": 2,
    "max_stack": 1,
    "can_trade": true,
    "can_sell": true,
    "can_drop": false,
    "can_destroy": true,
    "bind_type": 1,
    "use_level": 10,
    "use_vocation": 0,
    "expire_type": 0,
    "expire_time": 0,
    "use_skill_ids": [],
    "cooldown": 0,
    "cooldown_group": 0,
    "tags": [
      "equipment",
      "armor",
      "helmet"
    ]
  },
  {
    "id": 40001,
    "name": "小猫玩偶",
    "type": 4,
    "sub_type": 18,
    "rarity": 1,
    "quality": 1,
    "max_stack": 1,
    "can_trade": false,
    "can_sell": false,
    "can_drop": true,
    "can_destroy": false,
    "bind_type": 0,
    "use_level": 0,
    "use_vocation": 0,
    "expire_type": 0,
    "expire_time": 0,
    "use_skill_ids": [],
    "cooldown": 0,
    "cooldown_group": 0,
    "tags": []
  },
  {
    "id": 40002,
    "name": "小狗玩偶",
    "type": 4,
    "sub_type": 18,
    "rarity": 1,
    "quality": 1,
    "max_stack": 1,
    "can_trade": false,
    "can_sell": false,
    "can_drop": true,
    "can_destroy": false,
    "bind_type": 0,
    "use_level": 0,
    "use_vocation": 0,
    "expire_type": 0,
    "expire_time": 0,
    "use_skill_ids": [],
    "cooldown": 0,
    "cooldown_group": 0,
    "tags": []
  },
  {
    "id": 40003,
    "name": "兔子玩偶",
    "type": 4,
    "sub_type": 18,
    "rarity": 1,
    "quality": 1,
    "max_stack": 1,
    "can_trade": false,
    "can_sell": false,
    "can_drop": true,
    "can_destroy": false,
    "bind_type": 0,
    "use_level": 0,
    "use_vocation": 0,
    "expire_type": 0,
    "expire_time": 0,
    "use_skill_ids": [],
    "cooldown": 0,
    "cooldown_group": 0,
    "tags": []
  },
  {
    "id": 40101,
    "name": "狐狸玩偶",
    "type": 4,
    "sub_type": 18,
    "rarity": 3,
    "quality": 2,
    "max_stack": 1,
    "can_trade": false,
    "can_sell": false,
    "can_drop": true,
    "can_destroy": false,
    "bind_type": 0,
    "use_level": 0,
    "use_vocation": 0,
    "expire_type": 0,
    "expire_time": 0,
    "use_skill_ids": [],
    "cooldown": 0,
    "cooldown_group": 0,
    "tags": []
  },
  {
    "id": 40102,
    "name": "熊猫玩偶",
    "type": 4,
    "sub_type": 18,
    "rarity": 3,
    "quality": 2,
    "max_stack": 1,
    "can_trade": false,
    "can_sell": false,
    "can_drop": true,
    "can_destroy": false,
    "bind_type": 0,
    "use_level": 0,
    "use_vocation": 0,
    "expire_type": 0,
    "expire_time": 0,
    "use_skill_ids": [],
    "cooldown": 0,
    "cooldown_group": 0,
    "tags": []
  },
  {
    "id": 40201,
    "name": "幼龙玩偶",
    "type": 4,
    "sub_type": 18,
    "rarity": 4,
    "quality": 3,
    "max_stack": 1,
    "can_trade": false,
    "can_sell": false,
    "can_drop": true,
    "can_destroy": false,
    "bind_type": 0,
    "use_level": 0,
    "use_vocation": 0,
    "expire_type": 0,
    "expire_time": 0,
    "use_skill_ids": [],
    "cooldown": 0,
    "cooldown_group": 0,
    "tags": []
  },
  {
    "id": 40301,
    "name": "凤凰玩偶",
    "type": 4,
    "sub_type": 18,
    "rarity": 5,
    "quality": 4,
    "max_stack": 1,
    "can_trade": false,
    "can_sell": false,
    "can_drop": true,
    "can_destroy": false,
    "bind_type": 0,
    "use_level": 0,
    "use_vocation": 0,
    "expire_type": 0,
    "expire_time": 0,
    "use_skill_ids": [],
    "cooldown": 0,
    "cooldown_group": 0,
    "tags": []
  },
  {
    "id": 40004,
    "name": "骑士玩偶",
    "type": 4,
    "sub_type": 19,
    "rarity": 1,
    "quality": 1,
    "max_stack": 1,
    "can_trade": false,
    "can_sell": false,
    "can_drop": true,
    "can_destroy": false,
    "bind_type": 0,
    "use_level": 0,
    "use_vocation": 0,
    "expire_type": 0,
    "expire_time": 0,
    "use_skill_ids": [],
    "cooldown": 0,
    "cooldown_group": 0,
    "tags": []
  },
  {
    "id": 40005,
    "name": "法师玩偶",
    "type": 4,
    "sub_type": 19,
    "rarity": 1,
    "quality": 1,
    "max_stack": 1,
    "can_trade": false,
    "can_sell": false,
    "can_drop": true,
    "can_destroy": false,
    "bind_type": 0,
    "use_level": 0,
    "use_vocation": 0,
    "expire_type": 0,
    "expire_time": 0,
    "use_skill_ids": [],
    "cooldown": 0,
    "cooldown_group": 0,
    "tags": []
  },
  {
    "id": 40103,
    "name": "弓箭手玩偶",
    "type": 4,
    "sub_type": 19,
    "rarity": 3,
    "quality": 2,
    "max_stack": 1,
    "can_trade": false,
    "can_sell": false,
    "can_drop": true,
    "can_destroy": false,
    "bind_type": 0,
    "use_level": 0,
    "use_vocation": 0,
    "expire_type": 0,
    "expire_time": 0,
    "use_skill_ids": [],
    "cooldown": 0,
    "cooldown_group": 0,
    "tags": []
  },
  {
    "id": 40202,
    "name": "圣骑士玩偶",
    "type": 4,
    "sub_type": 19,
    "rarity": 4,
    "quality": 3,
    "max_stack": 1,
    "can_trade": false,
    "can_sell": false,
    "can_drop": true,
    "can_destroy": false,
    "bind_type": 0,
    "use_level": 0,
    "use_vocation": 0,
    "expire_type": 0,
    "expire_time": 0,
    "use_skill_ids": [],
    "cooldown": 0,
    "cooldown_group": 0,
    "tags": []
  },
  {
    "id": 40006,
    "name": "向日葵玩偶",
    "type": 4,
    "sub_type": 20,
    "rarity": 1,
    "quality": 1,
    "max_stack": 1,
    "can_trade": false,
    "can_sell": false,
    "can_drop": true,
    "can_destroy": false,
    "bind_type": 0,
    "use_level": 0,
    "use_vocation": 0,
    "expire_type": 0,
    "expire_time": 0,
    "use_skill_ids": [],
    "cooldown": 0,
    "cooldown_group": 0,
    "tags": []
  },
  {
    "id": 40104,
    "name": "玫瑰玩偶",
    "type": 4,
    "sub_type": 20,
    "rarity": 3,
    "quality": 2,
    "max_stack": 1,
    "can_trade": false,
    "can_sell": false,
    "can_drop": true,
    "can_destroy": false,
    "bind_type": 0,
    "use_level": 0,
    "use_vocation": 0,
    "expire_type": 0,
    "expire_time": 0,
    "use_skill_ids": [],
    "cooldown": 0,
    "cooldown_group": 0,
    "tags": []
  }
]